byted_odin_lib/__init__.py
byted_odin_lib-0.0.1.dist-info/METADATA
byted_odin_lib-0.0.1.dist-info/WHEEL
byted_odin_lib-0.0.1.dist-info/top_level.txt
byted_odin_lib-0.0.1.dist-info/RECORD
